active_alchemy.py
Active_Alchemy-1.1.0.dist-info/METADATA
Active_Alchemy-1.1.0.dist-info/RECORD
Active_Alchemy-1.1.0.dist-info/WHEEL
Active_Alchemy-1.1.0.dist-info/pbr.json
Active_Alchemy-1.1.0.dist-info/top_level.txt
