Metadata-Version: 2.1
Name: Active-Alchemy
Version: 1.1.0
Summary: A framework agnostic wrapper for SQLAlchemy with a simple active record like api
Home-page: http://github.com/mardix/active-alchemy/
Author: Mardix
Author-email: mardix@pylot.io
License: MIT
Download-URL: http://github.com/mardix/active-alchemy/tarball/master
Keywords: sqlalchemy,flask,active sqlalchemy,orm,active record,mysql,postgresql,pymysql,pg8000,sqlite
Platform: any
Classifier: Development Status :: 5 - Production/Stable
Classifier: Environment :: Web Environment
Classifier: Intended Audience :: Developers
Classifier: License :: OSI Approved :: MIT License
Classifier: Programming Language :: Python :: 2
Classifier: Programming Language :: Python :: 2.6
Classifier: Programming Language :: Python :: 2.7
Classifier: Programming Language :: Python :: 3
Classifier: Programming Language :: Python :: 3.3
Classifier: Programming Language :: Python :: 3.4
Classifier: Programming Language :: Python :: Implementation :: PyPy
Requires-Dist: SQLAlchemy
Requires-Dist: PyMySQL
Requires-Dist: pg8000
Requires-Dist: Paginator
Requires-Dist: inflection
Requires-Dist: arrow
Requires-Dist: sqlalchemy-utils
